ibes/__init__.py
ibes/objects/__init__.py
ibes/objects/base.py
ibes/objects/environments.py
ibes/objects/housekeeping.py
ibes/objects/organisms.py
ibes/objects/pools.py
ibes/objects/stressors.py
ibes/objects/structures.py
ibes/objects/variables.py
ibes/sim/__init__.py
ibes/sim/experiment.py
ibes/sim/simulation.py
ibes/utils/__init__.py
ibes/utils/config.py
ibes/utils/errors.py
ibes/utils/math_helpers.py
ibes/utils/misc.py
ibes-0.2.3.dist-info/LICENSE
ibes-0.2.3.dist-info/METADATA
ibes-0.2.3.dist-info/WHEEL
ibes-0.2.3.dist-info/top_level.txt
ibes-0.2.3.dist-info/RECORD
