Metadata-Version: 2.1
Name: ibes
Version: 0.2.3
Summary: Individual-based experiment simulation
Author-email: Florian Schunck <fluncki@protonmail.com>
License: MIT License
Project-URL: Homepage, https://github.com/flo-schu/timepath
Project-URL: Issue Tracker, https://github.com/flo-schu/timepath/issues
Classifier: Development Status :: 4 - Beta
Classifier: Programming Language :: Python :: 3
Classifier: Natural Language :: English
Classifier: License :: OSI Approved :: GNU General Public License v3 (GPLv3)
Classifier: Operating System :: OS Independent
Classifier: Topic :: Scientific/Engineering :: Bio-Informatics
Requires-Python: >=3.10
License-File: LICENSE
Requires-Dist: dpath ~=2.1.6
Requires-Dist: matplotlib ~=3.7.1
Requires-Dist: numpy ~=1.24.0
Requires-Dist: xarray ~=2023.11.0
Requires-Dist: pandas ~=2.0.2
Requires-Dist: prettytable ~=3.7.0
Requires-Dist: scipy ~=1.10.1
Requires-Dist: tqdm ~=4.65.0
Requires-Dist: toopy ==0.5.1
Provides-Extra: dev
Requires-Dist: pytest >=7.3 ; extra == 'dev'
Requires-Dist: pyinstrument >=4.5 ; extra == 'dev'
Requires-Dist: bumpver ; extra == 'dev'
